LICENSE
MANIFEST.in
README.rst
requirements.txt
requirements_2.7.txt
requirements_dev.txt
setup.py
fixed_openapi_core.egg-info/PKG-INFO
fixed_openapi_core.egg-info/SOURCES.txt
fixed_openapi_core.egg-info/dependency_links.txt
fixed_openapi_core.egg-info/not-zip-safe
fixed_openapi_core.egg-info/requires.txt
fixed_openapi_core.egg-info/top_level.txt
openapi_core/__init__.py
openapi_core/compat.py
openapi_core/shortcuts.py
openapi_core/extensions/__init__.py
openapi_core/extensions/models/__init__.py
openapi_core/extensions/models/factories.py
openapi_core/extensions/models/models.py
openapi_core/schema/__init__.py
openapi_core/schema/exceptions.py
openapi_core/schema/components/__init__.py
openapi_core/schema/components/factories.py
openapi_core/schema/components/models.py
openapi_core/schema/content/__init__.py
openapi_core/schema/content/exceptions.py
openapi_core/schema/content/models.py
openapi_core/schema/infos/__init__.py
openapi_core/schema/infos/factories.py
openapi_core/schema/infos/models.py
openapi_core/schema/links/__init__.py
openapi_core/schema/links/generators.py
openapi_core/schema/links/models.py
openapi_core/schema/media_types/__init__.py
openapi_core/schema/media_types/exceptions.py
openapi_core/schema/media_types/generators.py
openapi_core/schema/media_types/models.py
openapi_core/schema/operations/__init__.py
openapi_core/schema/operations/exceptions.py
openapi_core/schema/operations/generators.py
openapi_core/schema/operations/models.py
openapi_core/schema/parameters/__init__.py
openapi_core/schema/parameters/enums.py
openapi_core/schema/parameters/exceptions.py
openapi_core/schema/parameters/factories.py
openapi_core/schema/parameters/generators.py
openapi_core/schema/parameters/models.py
openapi_core/schema/paths/__init__.py
openapi_core/schema/paths/exceptions.py
openapi_core/schema/paths/generators.py
openapi_core/schema/paths/models.py
openapi_core/schema/properties/__init__.py
openapi_core/schema/properties/generators.py
openapi_core/schema/request_bodies/__init__.py
openapi_core/schema/request_bodies/exceptions.py
openapi_core/schema/request_bodies/factories.py
openapi_core/schema/request_bodies/models.py
openapi_core/schema/responses/__init__.py
