Metadata-Version: 2.1
Name: fixed-openapi-core
Version: 0.12.0
Summary: UNKNOWN
Home-page: https://github.com/ShagaleevAlexey/openapi-core
Author: Shagaleev Alexey
Author-email: alexey.shagaleev@yandex.ru
License: UNKNOWN
Platform: UNKNOWN
Classifier: Development Status :: 4 - Beta
Classifier: Intended Audience :: Developers
Classifier: Topic :: Software Development :: Libraries :: Python Modules
Classifier: Operating System :: OS Independent
Classifier: Programming Language :: Python :: 2.7
Classifier: Programming Language :: Python :: 3.5
Classifier: Programming Language :: Python :: 3.6
Classifier: Programming Language :: Python :: 3.7
Classifier: Topic :: Software Development :: Libraries
Provides-Extra: flask
